notetaking/__init__.py
notetaking/daemon.py
notetaking/notetaking.py
notetaking/css/default.css
notetaking/fonts/cmunbi.ttf
notetaking/fonts/cmunbtl.ttf
notetaking/fonts/cmunbto.ttf
notetaking/fonts/cmunbx.ttf
notetaking/fonts/cmunit.ttf
notetaking/fonts/cmunrm.ttf
notetaking/fonts/cmuntb.ttf
notetaking/fonts/cmunti.ttf
notetaking/fonts/cmuntt.ttf
notetaking/fonts/cmuntx.ttf
notetaking/fonts/cmunvi.ttf
notetaking/fonts/cmunvt.ttf
notetaking-0.1.4.dist-info/LICENSE
notetaking-0.1.4.dist-info/METADATA
notetaking-0.1.4.dist-info/WHEEL
notetaking-0.1.4.dist-info/entry_points.txt
notetaking-0.1.4.dist-info/top_level.txt
notetaking-0.1.4.dist-info/RECORD
