Metadata-Version: 2.1
Name: notetaking
Version: 0.1.4
Summary: Markdown -> HTML -> pdf on the fly
Home-page: UNKNOWN
Author: Calum Baird
Author-email: calum.baird7011@gmail.com
License: GPLv3
Keywords: markdown html pdf weasyprint
Platform: UNKNOWN
Classifier: Development Status :: 3 - Alpha
Classifier: License :: OSI Approved :: GNU General Public License v3 (GPLv3)
Classifier: Programming Language :: Python :: 3
Classifier: Topic :: Text Processing :: Markup
Requires-Python: >=3.6
Requires-Dist: markdown
Requires-Dist: weasyprint
Requires-Dist: inotify
Requires-Dist: pygments
Requires-Dist: cairocffi
